drumterm/__init__.py
drumterm/main.py
drumterm/sounds/cowbell.wav
drumterm/sounds/crash.wav
drumterm/sounds/hihat_closed.wav
drumterm/sounds/hihat_open.wav
drumterm/sounds/kick.wav
drumterm/sounds/snare.wav
drumterm/sounds/tom_high.wav
drumterm/sounds/tom_low.wav
drumterm/sounds/tom_mid.wav
drumterm-0.1.1.dist-info/licenses/LICENSE
drumterm-0.1.1.dist-info/METADATA
drumterm-0.1.1.dist-info/WHEEL
drumterm-0.1.1.dist-info/entry_points.txt
drumterm-0.1.1.dist-info/top_level.txt
drumterm-0.1.1.dist-info/RECORD
